{
    "particleeffect": {
        "activetime": {
            "value": "1.0"
        },
        "colorfade": [
            {
                "color": "0.0000 0.0000 0.0000 0.0000",
                "time": "0.0"
            },
            {
                "color": "0.0000 0.0000 0.0000 1.0000",
                "time": "1.768421052631579"
            },
            {
                "color": "0.0000 0.0000 0.0000 1.0000",
                "time": "6.947368421052632"
            },
            {
                "color": "0.0000 0.0000 0.0000 1.0000",
                "time": "8.0"
            }
        ],
        "depthtest": {
            "enable": "true"
        },
        "direction": {
            "max": "0.0 0.0 0.0",
            "min": "0.0 0.0 0.0",
            "value": "Direction"
        },
        "emitterScaleCurve": [

        ],
        "emitterscale": [

        ],
        "emittersize": {
            "value": "0.0 0.0 0.0"
        },
        "emittertype": {
            "value": "Sphere"
        },
        "faceCameraMode": {
            "value": "Horizontal"
        },
        "inactivetime": {
            "value": "1.0"
        },
        "numparticles": {
            "value": "2"
        },
        "particlesize": {
            "max": "1.2 1.2",
            "min": "1.3 1.3"
        },
        "relative": {
            "enable": "true"
        },
        "rotation": {
            "max": "180.0",
            "min": "0.0"
        },
        "sizedelta": [
            {
                "scale": "0.54 0.54",
                "time": "0.00"
            },
            {
                "scale": "1.14 1.14",
                "time": "1.60"
            },
            {
                "scale": "1.32 1.32",
                "time": "3.00"
            }
        ],
        "texture": {
            "ani": {
                "fps": "7",
                "name": "textures/sfxs/netease_round_debuff_heiyan2",
                "shuffle": false
            },
            "name": "textures/sfxs/netease_round_trap_heiquan2"
        },
        "thickness": {
            "value": "0.0"
        },
        "timetolive": {
            "max": "2.0",
            "min": "1.5"
        }
    }
}