{
  "_comment": "当前插件名字",
  "netgame_mod_name": "neteaseMenusDev",
  "_comment": "插件版本",
  "netgame_mod_version": "1.0.5",
  "_comment": "最低引擎版本",
  "min_app_version": "1.21.0.release20210401",
  "_comment": "插件实现的功能",
  "description": "定义主菜单按钮",
  "_comment": "列表，支持的服务器类型，包括game/lobby/master/service几种类型",
  "support_server_type": [
    "lobby",
    "game"
  ],
  "_comment": "作者，官方插件作者统一是NetEase",
  "author": "NetEase",
  "_comment": "所属插件组合的名字，主菜单插件由lobby/game插件组合而成",
  "group": "neteaseMenus",

  "_comment": "以下为可配置项",
  "_comment": "主菜单配置",
  "configParams": {
    "_comment": "最大列数",
    "maxColumnNum": 4,
    "_comment": "菜单的按钮配置，按照list的顺序从左到右、从上到下排布",
    "menusConfig": [
      {
        "_comment": "按钮名字，用于标识不同按钮，且在点击后作为回调参数",
        "name": "Menu1",
        "_comment": "按钮显示的文字，不超过5个字",
        "normal_text": "菜单1",
        "_comment": "按钮普通状态时的贴图",
        "normal_icon": "textures/ui/netease_menu/icon01@3x",
        "_comment": "按钮按下状态时的贴图",
        "normal_pressed": "textures/ui/netease_menu/icon01@3x",
        "_comment": "按钮悬浮状态时的贴图",
        "normal_hover": "textures/ui/netease_menu/icon01@3x",
        "_comment": "按钮被禁用时显示的文字，一般用于显示解锁条件，比如显示“14级解锁”，不超过5个字",
        "disabled_text": "14级解锁",
        "_comment": "按钮被禁用时普通状态时的贴图",
        "disabled_icon": "textures/ui/netease_menu/icon01_disable@3x",
        "_comment": "按钮被禁用时按下状态时的贴图",
        "disabled_pressed": "textures/ui/netease_menu/icon01_disable@3x",
        "_comment": "按钮被禁用时悬浮状态时的贴图",
        "disabled_hover": "textures/ui/netease_menu/icon01_disable@3x",
        "_comment": "是否开启这个按钮，可以在服务端动态调整以控制对应客户端按钮状态，开启：True，禁用：False，隐藏：服务端不要下发",
        "enabled": true
      },
      {
        "_comment": "按钮名字，用于标识不同按钮，且在点击后作为回调参数",
        "name": "Menu2",
        "_comment": "按钮显示的文字，不超过5个字",
        "normal_text": "菜单2",
        "_comment": "按钮普通状态时的贴图",
        "normal_icon": "textures/ui/netease_menu/icon01@3x",
        "_comment": "按钮按下状态时的贴图",
        "normal_pressed": "textures/ui/netease_menu/icon01@3x",
        "_comment": "按钮悬浮状态时的贴图",
        "normal_hover": "textures/ui/netease_menu/icon01@3x",
        "_comment": "按钮被禁用时显示的文字，一般用于显示解锁条件，比如显示“14级解锁”，不超过5个字",
        "disabled_text": "14级解锁",
        "_comment": "按钮被禁用时普通状态时的贴图",
        "disabled_icon": "textures/ui/netease_menu/icon01_disable@3x",
        "_comment": "按钮被禁用时按下状态时的贴图",
        "disabled_pressed": "textures/ui/netease_menu/icon01_disable@3x",
        "_comment": "按钮被禁用时悬浮状态时的贴图",
        "disabled_hover": "textures/ui/netease_menu/icon01_disable@3x",
        "_comment": "是否开启这个按钮，可以在服务端动态调整以控制对应客户端按钮状态",
        "enabled": true
      },
      {
        "_comment": "按钮名字，用于标识不同按钮，且在点击后作为回调参数",
        "name": "Menu3",
        "_comment": "按钮显示的文字，不超过5个字",
        "normal_text": "菜单2",
        "_comment": "按钮普通状态时的贴图",
        "normal_icon": "textures/ui/netease_menu/icon01@3x",
        "_comment": "按钮按下状态时的贴图",
        "normal_pressed": "textures/ui/netease_menu/icon01@3x",
        "_comment": "按钮悬浮状态时的贴图",
        "normal_hover": "textures/ui/netease_menu/icon01@3x",
        "_comment": "按钮被禁用时显示的文字，一般用于显示解锁条件，比如显示“14级解锁”，不超过5个字",
        "disabled_text": "14级解锁",
        "_comment": "按钮被禁用时普通状态时的贴图",
        "disabled_icon": "textures/ui/netease_menu/icon01_disable@3x",
        "_comment": "按钮被禁用时按下状态时的贴图",
        "disabled_pressed": "textures/ui/netease_menu/icon01_disable@3x",
        "_comment": "按钮被禁用时悬浮状态时的贴图",
        "disabled_hover": "textures/ui/netease_menu/icon01_disable@3x",
        "_comment": "是否开启这个按钮，可以在服务端动态调整以控制对应客户端按钮状态",
        "enabled": false
      },
      {
        "_comment": "按钮名字，用于标识不同按钮，且在点击后作为回调参数",
        "name": "Menu4",
        "_comment": "按钮显示的文字，不超过5个字",
        "normal_text": "菜单2",
        "_comment": "按钮普通状态时的贴图",
        "normal_icon": "textures/ui/netease_menu/icon01@3x",
        "_comment": "按钮按下状态时的贴图",
        "normal_pressed": "textures/ui/netease_menu/icon01@3x",
        "_comment": "按钮悬浮状态时的贴图",
        "normal_hover": "textures/ui/netease_menu/icon01@3x",
        "_comment": "按钮被禁用时显示的文字，一般用于显示解锁条件，比如显示“14级解锁”，不超过5个字",
        "disabled_text": "14级解锁",
        "_comment": "按钮被禁用时普通状态时的贴图",
        "disabled_icon": "textures/ui/netease_menu/icon01_disable@3x",
        "_comment": "按钮被禁用时按下状态时的贴图",
        "disabled_pressed": "textures/ui/netease_menu/icon01_disable@3x",
        "_comment": "按钮被禁用时悬浮状态时的贴图",
        "disabled_hover": "textures/ui/netease_menu/icon01_disable@3x",
        "_comment": "是否开启这个按钮，可以在服务端动态调整以控制对应客户端按钮状态",
        "enabled": false
      },
      {
        "_comment": "按钮名字，用于标识不同按钮，且在点击后作为回调参数",
        "name": "Menu5",
        "_comment": "按钮显示的文字，不超过5个字",
        "normal_text": "菜单2",
        "_comment": "按钮普通状态时的贴图",
        "normal_icon": "textures/ui/netease_menu/icon01@3x",
        "_comment": "按钮按下状态时的贴图",
        "normal_pressed": "textures/ui/netease_menu/icon01@3x",
        "_comment": "按钮悬浮状态时的贴图",
        "normal_hover": "textures/ui/netease_menu/icon01@3x",
        "_comment": "按钮被禁用时显示的文字，一般用于显示解锁条件，比如显示“14级解锁”，不超过5个字",
        "disabled_text": "14级解锁",
        "_comment": "按钮被禁用时普通状态时的贴图",
        "disabled_icon": "textures/ui/netease_menu/icon01_disable@3x",
        "_comment": "按钮被禁用时按下状态时的贴图",
        "disabled_pressed": "textures/ui/netease_menu/icon01_disable@3x",
        "_comment": "按钮被禁用时悬浮状态时的贴图",
        "disabled_hover": "textures/ui/netease_menu/icon01_disable@3x",
        "_comment": "是否开启这个按钮，可以在服务端动态调整以控制对应客户端按钮状态",
        "enabled": false
      },
      {
        "_comment": "按钮名字，用于标识不同按钮，且在点击后作为回调参数",
        "name": "Menu6",
        "_comment": "按钮显示的文字，不超过5个字",
        "normal_text": "菜单2",
        "_comment": "按钮普通状态时的贴图",
        "normal_icon": "textures/ui/netease_menu/icon01@3x",
        "_comment": "按钮按下状态时的贴图",
        "normal_pressed": "textures/ui/netease_menu/icon01@3x",
        "_comment": "按钮悬浮状态时的贴图",
        "normal_hover": "textures/ui/netease_menu/icon01@3x",
        "_comment": "按钮被禁用时显示的文字，一般用于显示解锁条件，比如显示“14级解锁”，不超过5个字",
        "disabled_text": "14级解锁",
        "_comment": "按钮被禁用时普通状态时的贴图",
        "disabled_icon": "textures/ui/netease_menu/icon01_disable@3x",
        "_comment": "按钮被禁用时按下状态时的贴图",
        "disabled_pressed": "textures/ui/netease_menu/icon01_disable@3x",
        "_comment": "按钮被禁用时悬浮状态时的贴图",
        "disabled_hover": "textures/ui/netease_menu/icon01_disable@3x",
        "_comment": "是否开启这个按钮，可以在服务端动态调整以控制对应客户端按钮状态",
        "enabled": false
      },
      {
        "_comment": "按钮名字，用于标识不同按钮，且在点击后作为回调参数",
        "name": "Menu7",
        "_comment": "按钮显示的文字，不超过5个字",
        "normal_text": "菜单2",
        "_comment": "按钮普通状态时的贴图",
        "normal_icon": "textures/ui/netease_menu/icon01@3x",
        "_comment": "按钮按下状态时的贴图",
        "normal_pressed": "textures/ui/netease_menu/icon01@3x",
        "_comment": "按钮悬浮状态时的贴图",
        "normal_hover": "textures/ui/netease_menu/icon01@3x",
        "_comment": "按钮被禁用时显示的文字，一般用于显示解锁条件，比如显示“14级解锁”，不超过5个字",
        "disabled_text": "14级解锁",
        "_comment": "按钮被禁用时普通状态时的贴图",
        "disabled_icon": "textures/ui/netease_menu/icon01_disable@3x",
        "_comment": "按钮被禁用时按下状态时的贴图",
        "disabled_pressed": "textures/ui/netease_menu/icon01_disable@3x",
        "_comment": "按钮被禁用时悬浮状态时的贴图",
        "disabled_hover": "textures/ui/netease_menu/icon01_disable@3x",
        "_comment": "是否开启这个按钮，可以在服务端动态调整以控制对应客户端按钮状态",
        "enabled": false
      },
      {
        "_comment": "按钮名字，用于标识不同按钮，且在点击后作为回调参数",
        "name": "Menu8",
        "_comment": "按钮显示的文字，不超过5个字",
        "normal_text": "菜单2",
        "_comment": "按钮普通状态时的贴图",
        "normal_icon": "textures/ui/netease_menu/icon01@3x",
        "_comment": "按钮按下状态时的贴图",
        "normal_pressed": "textures/ui/netease_menu/icon01@3x",
        "_comment": "按钮悬浮状态时的贴图",
        "normal_hover": "textures/ui/netease_menu/icon01@3x",
        "_comment": "按钮被禁用时显示的文字，一般用于显示解锁条件，比如显示“14级解锁”，不超过5个字",
        "disabled_text": "14级解锁",
        "_comment": "按钮被禁用时普通状态时的贴图",
        "disabled_icon": "textures/ui/netease_menu/icon01_disable@3x",
        "_comment": "按钮被禁用时按下状态时的贴图",
        "disabled_pressed": "textures/ui/netease_menu/icon01_disable@3x",
        "_comment": "按钮被禁用时悬浮状态时的贴图",
        "disabled_hover": "textures/ui/netease_menu/icon01_disable@3x",
        "_comment": "是否开启这个按钮，可以在服务端动态调整以控制对应客户端按钮状态",
        "enabled": false
      },
      {
        "_comment": "按钮名字，用于标识不同按钮，且在点击后作为回调参数",
        "name": "Menu8",
        "_comment": "按钮显示的文字，不超过5个字",
        "normal_text": "菜单2",
        "_comment": "按钮普通状态时的贴图",
        "normal_icon": "textures/ui/netease_menu/icon01@3x",
        "_comment": "按钮按下状态时的贴图",
        "normal_pressed": "textures/ui/netease_menu/icon01@3x",
        "_comment": "按钮悬浮状态时的贴图",
        "normal_hover": "textures/ui/netease_menu/icon01@3x",
        "_comment": "按钮被禁用时显示的文字，一般用于显示解锁条件，比如显示“14级解锁”，不超过5个字",
        "disabled_text": "14级解锁",
        "_comment": "按钮被禁用时普通状态时的贴图",
        "disabled_icon": "textures/ui/netease_menu/icon01_disable@3x",
        "_comment": "按钮被禁用时按下状态时的贴图",
        "disabled_pressed": "textures/ui/netease_menu/icon01_disable@3x",
        "_comment": "按钮被禁用时悬浮状态时的贴图",
        "disabled_hover": "textures/ui/netease_menu/icon01_disable@3x",
        "_comment": "是否开启这个按钮，可以在服务端动态调整以控制对应客户端按钮状态",
        "enabled": false
      }
    ]
  }
}